encab_gelf/__init__.py
encab_gelf/config.py
encab_gelf/encab_gelf.py
encab_gelf/handlers.py
encab_gelf/log_line_recognizer.py
encab_gelf/one_shot_timer.py
encab_gelf/gelf/__init__.py
encab_gelf/gelf/gelf.py
encab_gelf/gelf/handlers.py
encab_gelf-0.0.4.dist-info/LICENSE
encab_gelf-0.0.4.dist-info/METADATA
encab_gelf-0.0.4.dist-info/WHEEL
encab_gelf-0.0.4.dist-info/top_level.txt
encab_gelf-0.0.4.dist-info/RECORD
