Metadata-Version: 2.2
Name: encab_gelf
Version: 0.0.4
Summary: GELF extension for encab process manager
Author-email: Sebastian Kuebeck <sebastian.kuebeck@encab.io>
Project-URL: Homepage, https://github.com/sebastian-kuebeck/encab_gelf
Project-URL: Documentation, https://github.com/sebastian-kuebeck/encab_gelf/README.MD
Project-URL: Bug Tracker, https://github.com/sebastian-kuebeck/encab_gelf
Classifier: Programming Language :: Python :: 3.9
Classifier: Programming Language :: Python :: 3.10
Classifier: Programming Language :: Python :: 3.11
Classifier: Programming Language :: Python :: 3.12
Classifier: Programming Language :: Python :: 3.13
Classifier: License :: OSI Approved :: MIT License
Classifier: Operating System :: OS Independent
Requires-Python: >=3.9
License-File: LICENSE
Requires-Dist: encab<2,>=1.0.1
Requires-Dist: pygrok<2,>=1.0.0
